easyfileio/__init__.py
easyfileio/main.py
easyfileio-1.22.dist-info/METADATA
easyfileio-1.22.dist-info/WHEEL
easyfileio-1.22.dist-info/top_level.txt
easyfileio-1.22.dist-info/RECORD
