Metadata-Version: 2.4
Name: easyfileio
Version: 1.22
Summary: an easy way to read and write files in python
Home-page: https://github.com/plzgivemeajob/easyfileio
Author-email: zeemako@gmail.com
License: MIT
Dynamic: author-email
Dynamic: description
Dynamic: description-content-type
Dynamic: home-page
Dynamic: license
Dynamic: summary
